Workbook

Sheet Sheet1
A1: order_id | B1: region | C1: category | D1: sales | E1: discount | F1: quantity | G1: order_date | H1: delivery_date | I1: customer_type | J1: payment_mode | K1: profit | L1: city
A2: ORD100000 | B2: East | C2: Clothing | D2: 713.49 | E2: 0.31 | F2: 3 | G2: 45015 | H2: 45017 | I2: Member | J2: UPI | K2: 114.72 | L2: Pune
A3: ORD100001 | B3: West | C3: Electronics | D3: 3802.97 | E3: 0.38 | F3: 4 | G3: 45166 | H3: 45172 | I3: Regular | J3: Card | K3: 971.41 | L3: Hyderabad
A4: ORD100002 | B4: North | C4: Home Care | D4: 3588.97 | E4: 0.1 | F4: 7 | G4: 45360 | H4: 45366 | I4: Regular | J4: Cash | K4: 769.08 | L4: Bangalore | P4: RECORDS | R4: REVENUE
A5: ORD100003 | B5: East | C5: Electronics | D5: 1160.86 | E5: 0.27 | F5: 5 | G5: 45578 | H5: 45584 | I5: Member | J5: UPI | K5: 71.61 | L5: Pune
A6: ORD100004 | B6: East | C6: Electronics | D6: 3071.32 | E6: 0 | F6: 7 | G6: 45022 | H6: 45025 | I6: New | J6: Cash | K6: 621.92 | L6: Bangalore | P6: PROFIT ON REGIONS | R6: {=s} -> #NAME?
A7: ORD100005 | B7: West | C7: Grocery | D7: 2566.18 | E7: 0.02 | F7: 6 | G7: 45108 | H7: 45111 | I7: Member | J7: UPI | K7: 578.94 | L7: Mumbai | N7: NORTH | P7: =SUMIF(B:B,"north",K:K) -> 1769020.9
A8: ORD100006 | B8: North | C8: Personal Care | D8: 398 | E8: 0.16 | F8: 4 | G8: 45119 | H8: 45124 | I8: New | J8: Cash | K8: 110.31 | L8: Mumbai | N8: =SUMIF(B:B,"North",D:D) -> 10143913
A9: ORD100007 | B9: North | C9: Personal Care | D9: 1462.95 | E9: 0.23 | F9: 2 | G9: 45064 | H9: 45066 | I9: Regular | J9: UPI | K9: 91.68 | L9: Bangalore | N9: EAST | P9: =SUMIF(B:B,"EAST",K:K) -> 1675277.8
A10: ORD100008 | B10: East | C10: Personal Care | D10: 4997.47 | E10: 0.29 | F10: 6 | G10: 45296 | H10: 45299 | I10: Regular | J10: Card | K10: 995.78 | L10: Delhi | N10: =SUMIF(B:B,"east",D:D) -> 9518321.9
A11: ORD100009 | B11: South | C11: Grocery | D11: 587.72 | E11: 0.44 | F11: 6 | G11: 45514 | H11: 45521 | I11: New | J11: Cash | K11: 102.96 | L11: Pune | N11: WEST | P11: =SUMIF(B:B,"WEST",K:K) -> 1713802.1
A12: ORD100010 | B12: East | C12: Clothing | D12: 2581.42 | E12: 0.39 | F12: 6 | G12: 45419 | H12: 45420 | I12: Regular | J12: Cash | K12: 542.82 | L12: Bangalore | N12: =SUMIF(B:B,"west",D:D) -> 9748863.1
A13: ORD100011 | B13: East | C13: Clothing | D13: 4261.74 | E13: 0.15 | F13: 1 | G13: 45171 | H13: 45172 | I13: New | J13: UPI | K13: 1028.47 | L13: Pune | N13: SOUTH | P13: =SUMIF(B:B,"SOUTH",K:K) -> 1714039
A14: ORD100012 | B14: East | C14: Home Care | D14: 1573.19 | E14: 0.37 | F14: 6 | G14: 45331 | H14: 45338 | I14: New | J14: Cash | K14: 131.5 | L14: Bangalore | N14: =SUMIF(B:B,"south",D:D) -> 9851779.2
A15: ORD100013 | B15: East | C15: Clothing | D15: 1377.47 | E15: 0.27 | F15: 2 | G15: 45074 | H15: 45075 | I15: Member | J15: Cash | K15: 255.49 | L15: Delhi
A16: ORD100014 | B16: West | C16: Clothing | D16: 4464.89 | E16: 0.39 | F16: 5 | G16: 45296 | H16: 45303 | I16: Regular | J16: UPI | K16: 804.36 | L16: Pune
A17: ORD100015 | B17: North | C17: Personal Care | D17: 1593.67 | E17: 0.21 | F17: 7 | G17: 45583 | H17: 45587 | I17: Member | J17: Card | K17: 284.91 | L17: Chennai
A18: ORD100016 | B18: West | C18: Electronics | D18: 3292.32 | E18: 0.05 | F18: 1 | G18: 45042 | H18: 45043 | I18: Member | J18: Card | K18: 504.83 | L18: Mumbai
A19: ORD100017 | B19: West | C19: Clothing | D19: 3727.53 | E19: 0.31 | F19: 5 | G19: 45228 | H19: 45235 | I19: Regular | J19: Card | K19: 978.07 | L19: Chennai
A20: ORD100018 | B20: West | C20: Clothing | D20: 3964.23 | E20: 0.28 | F20: 9 | G20: 45448 | H20: 45451 | I20: Member | J20: UPI | K20: 260.95 | L20: Bangalore
A21: ORD100019 | B21: East | C21: Grocery | D21: 4974.32 | E21: 0.48 | F21: 3 | G21: 45047 | H21: 45051 | I21: Regular | J21: Card | K21: 727.29 | L21: Delhi
A22: ORD100020 | B22: South | C22: Home Care | D22: 4035.64 | E22: 0.08 | F22: 2 | G22: 45586 | H22: 45593 | I22: Regular | J22: Cash | K22: 798.81 | L22: Delhi
A23: ORD100021 | B23: North | C23: Grocery | D23: 3319.36 | E23: 0.33 | F23: 2 | G23: 45153 | H23: 45159 | I23: Member | J23: Cash | K23: 920.22 | L23: Bangalore
A24: ORD100022 | B24: South | C24: Personal Care | D24: 4487.77 | E24: 0.24 | F24: 3 | G24: 45657 | H24: 45659 | I24: Regular | J24: Card | K24: 931.37 | L24: Pune
A25: ORD100023 | B25: West | C25: Electronics | D25: 4538.15 | E25: 0.19 | F25: 1 | G25: 45005 | H25: 45008 | I25: Regular | J25: Cash | K25: 375.7 | L25: Delhi
A26: ORD100024 | B26: West | C26: Home Care | D26: 4868.52 | E26: 0.4 | F26: 2 | G26: 45272 | H26: 45273 | I26: Regular | J26: Cash | K26: 1072.26 | L26: Mumbai
... A15346: ORD115344 | B15346: South | C15346: Grocery | D15346: 4984.32 | E15346: 0.21 | F15346: 3 | G15346: 45248 | H15346: 45249 | I15346: New | J15346: Card | K15346: 909.1 | L15346: Bangalore

Sheet Sheet3
A1: Q1 | B1: Q2 | C1: Q3 | D1: Q4 | E1: Q5 | F1: Q6 | G1: Q7 | H1: Q8
A2: TOTAL NUMBERS OF RECORD | B2: NUMBERS OF CITYS | C2: TOTAL SALES | D2: AVG DISCOUNT | E2: PAYMENT TYPE | F2: PRODUCT CATEGORY | G2: PROFIT | H2: TYPES OF CUSTOMERS
A3: ANSWERS
A4: =COUNTA(Sheet1!A:A) -> 15346 | B4: =COUNTA(P7:P12) -> 6 | C4: =AVERAGE(Sheet1!D:D) -> 2558.6756 | D4: =AVERAGE(Sheet1!E:E) -> 0.2504288 | E4: =COUNTA(Q7:Q9) -> 3 | F4: =COUNTA(R11:R15) -> 5 | G4: =AVERAGE(Sheet1!K:K) -> 447.84228 | H4: =COUNTA(S8:S10) -> 3
P6: {=_xlfn.UNIQUE(Sheet1!L:L)} -> city | Q6: {=_xlfn.UNIQUE(Sheet1!J:J)} -> payment_mode
P7: Pune | Q7: UPI | S7: {=_xlfn.UNIQUE(Sheet1!I:I)} -> customer_type
P8: Hyderabad | Q8: Card | S8: Member
P9: Bangalore | Q9: Cash | S9: Regular
P10: Mumbai | Q10: 0 | R10: {=_xlfn.UNIQUE(Sheet1!C:C)} -> category | S10: New
P11: Delhi | R11: Clothing | S11: 0
P12: Chennai | R12: Electronics
P13: 0 | R13: Home Care
R14: Grocery
R15: Personal Care
R16: 0

Sheet Sheet2
A1: TOTAL NUMBERS OF RECORD | D1: NUMBERS OF CITYS | G1: TOTAL SALES | J1: AVG DISCOUNT | M1: PAYMENT TYPE | P1: PRODUCT CATEGORY
A3: =COUNT(Sheet1!D:D) -> 15345 | D3: {=_xlfn.UNIQUE(Sheet1!L:L)} -> city | G3: =AVERAGE(Sheet1!D:D) -> 2558.6756 | J3: =AVERAGE(Sheet1!E:E) -> 0.2504288 | M3: {=_xlfn.UNIQUE(Sheet1!J:J)} -> payment_mode | P3: {=_xlfn.UNIQUE(Sheet1!C:C)} -> category
D4: Pune | M4: UPI | P4: Clothing
D5: Hyderabad | M5: Card | P5: Electronics
D6: Bangalore | M6: Cash | P6: Home Care
D7: Mumbai | M7: 0 | P7: Grocery
D8: Delhi | M8: =COUNTA(M4:M6) -> 3 | P8: Personal Care
D9: Chennai | P9: 0
D10: 0 | P10: =COUNTA(P3:P8)-1 -> 5
D11: =COUNTA(D4:D9) -> 6
A14: PROFIT | D14: TYPR OF CUSTOMERS
A16: =SUM(Sheet1!K:K) -> 6872139.8 | D16: {=_xlfn.UNIQUE(Sheet1!I:I)} -> customer_type
D17: Member
D18: Regular
D19: New
D20: 0
D21: =COUNTA(D17:D19) -> 3
